alphaplinkpython/PlinkType.cpython-36m-x86_64-linux-gnu.so
alphaplinkpython/__init__.py
alphaplinkpython/PlinkWriter.cpython-36m-x86_64-linux-gnu.so
alphaplinkpython-0.0.8.dist-info/WHEEL
alphaplinkpython-0.0.8.dist-info/top_level.txt
alphaplinkpython-0.0.8.dist-info/METADATA
alphaplinkpython-0.0.8.dist-info/RECORD
