Metadata-Version: 2.1
Name: alphaplinkpython
Version: 0.0.8
Summary: AlphaGenes library for dealitng with plink
Home-page: UNKNOWN
Author: david
Author-email: david.wilson@roslin.ed.ac.uk
License: GPL
Platform: UNKNOWN
Requires-Dist: numpy
Requires-Dist: cython (>=0.26)
